modulus/__init__.py
modulus/constants.py
modulus/datapipes/__init__.py
modulus/datapipes/datapipe.py
modulus/datapipes/meta.py
modulus/datapipes/benchmarks/__init__.py
modulus/datapipes/benchmarks/darcy.py
modulus/datapipes/benchmarks/kelvin_helmholtz.py
modulus/datapipes/benchmarks/kernels/__init__.py
modulus/datapipes/benchmarks/kernels/finite_difference.py
modulus/datapipes/benchmarks/kernels/finite_volume.py
modulus/datapipes/benchmarks/kernels/indexing.py
modulus/datapipes/benchmarks/kernels/initialization.py
modulus/datapipes/benchmarks/kernels/utils.py
modulus/datapipes/cae/__init__.py
modulus/datapipes/cae/mesh_datapipe.py
modulus/datapipes/cae/readers.py
modulus/datapipes/climate/__init__.py
modulus/datapipes/climate/climate.py
modulus/datapipes/climate/era5_hdf5.py
modulus/datapipes/climate/era5_netcdf.py
modulus/datapipes/climate/synthetic.py
modulus/datapipes/climate/utils/__init__.py
modulus/datapipes/climate/utils/invariant.py
modulus/datapipes/climate/utils/zenith_angle.py
modulus/datapipes/gnn/__init__.py
modulus/datapipes/gnn/ahmed_body_dataset.py
modulus/datapipes/gnn/bsms.py
modulus/datapipes/gnn/drivaernet_dataset.py
modulus/datapipes/gnn/lagrangian_dataset.py
modulus/datapipes/gnn/lagrangian_reading_utils.py
modulus/datapipes/gnn/stokes_dataset.py
modulus/datapipes/gnn/utils.py
modulus/datapipes/gnn/vortex_shedding_dataset.py
modulus/datapipes/gnn/vortex_shedding_re300_1000_dataset.py
modulus/datapipes/healpix/__init__.py
modulus/datapipes/healpix/coupledtimeseries_dataset.py
modulus/datapipes/healpix/couplers.py
modulus/datapipes/healpix/data_modules.py
modulus/datapipes/healpix/timeseries_dataset.py
modulus/deploy/__init__.py
modulus/deploy/onnx/__init__.py
modulus/deploy/onnx/utils.py
modulus/deploy/triton/__init__.py
modulus/deploy/trt/__init__.py
modulus/distributed/__init__.py
modulus/distributed/autograd.py
modulus/distributed/config.py
modulus/distributed/fft.py
modulus/distributed/manager.py
modulus/distributed/mappings.py
nvidia_modulus-0.9.0.dist-info/LICENSE.txt
nvidia_modulus-0.9.0.dist-info/METADATA
nvidia_modulus-0.9.0.dist-info/WHEEL
nvidia_modulus-0.9.0.dist-info/entry_points.txt
nvidia_modulus-0.9.0.dist-info/top_level.txt
nvidia_modulus-0.9.0.dist-info/RECORD
