Metadata-Version: 2.1
Name: nvidia-modulus
Version: 0.9.0
Summary: A deep learning framework for AI-driven multi-physics systems
Author: NVIDIA Modulus Team
License: Apache 2.0
Project-URL: Homepage, https://github.com/NVIDIA/modulus
Project-URL: Documentation, https://docs.nvidia.com/modulus/#core
Project-URL: Issues, https://github.com/NVIDIA/modulus/issues
Project-URL: Changelog, https://github.com/NVIDIA/modulus/blob/main/CHANGELOG.md
Classifier: Programming Language :: Python :: 3
Classifier: License :: OSI Approved :: Apache Software License
Classifier: Operating System :: OS Independent
Requires-Python: >=3.10
License-File: LICENSE.txt
Requires-Dist: torch >=2.0.0
Requires-Dist: numpy <1.25,>=1.22.4
Requires-Dist: xarray >=2023.1.0
Requires-Dist: zarr >=2.14.2
Requires-Dist: fsspec >=2023.1.0
Requires-Dist: s3fs >=2023.5.0
Requires-Dist: nvidia-dali-cuda120 >=1.35.0
Requires-Dist: setuptools >=67.6.0
Requires-Dist: certifi >=2023.7.22
Requires-Dist: pytz >=2023.3
Requires-Dist: treelib >=1.2.5
Requires-Dist: tqdm >=4.60.0
Requires-Dist: nvtx >=0.2.8
Requires-Dist: onnx >=1.14.0
Requires-Dist: timm >=0.9.12
Provides-Extra: all
Requires-Dist: h5py >=3.7.0 ; extra == 'all'
Requires-Dist: netcdf4 >=1.6.3 ; extra == 'all'
Requires-Dist: ruamel.yaml >=0.17.22 ; extra == 'all'
Requires-Dist: scikit-learn >=1.0.2 ; extra == 'all'
Requires-Dist: scikit-image >=0.24.0 ; extra == 'all'
Requires-Dist: warp-lang >=1.0 ; extra == 'all'
Requires-Dist: vtk >=9.2.6 ; extra == 'all'
Requires-Dist: pyvista >=0.40.1 ; extra == 'all'
Requires-Dist: cftime >=1.6.2 ; extra == 'all'
Requires-Dist: einops >=0.7.0 ; extra == 'all'
Requires-Dist: pyspng >=0.1.0 ; extra == 'all'
Requires-Dist: shapely >=2.0.6 ; extra == 'all'
Requires-Dist: nvidia-modulus[launch] ; extra == 'all'
Requires-Dist: nvidia-modulus[dev] ; extra == 'all'
Requires-Dist: nvidia-modulus[makani] ; extra == 'all'
Requires-Dist: nvidia-modulus[fignet] ; extra == 'all'
Provides-Extra: dev
Requires-Dist: pytest >=6.0.0 ; extra == 'dev'
Requires-Dist: pyyaml >=6.0 ; extra == 'dev'
Requires-Dist: black ==22.10.0 ; extra == 'dev'
Requires-Dist: interrogate ==1.5.0 ; extra == 'dev'
Requires-Dist: coverage ==6.5.0 ; extra == 'dev'
Requires-Dist: ruff ==0.0.290 ; extra == 'dev'
Provides-Extra: fignet
Requires-Dist: jaxtyping >=0.2 ; extra == 'fignet'
Requires-Dist: torch-scatter >=2.1 ; extra == 'fignet'
Requires-Dist: torchinfo >=1.8 ; extra == 'fignet'
Requires-Dist: warp-lang >=1.0 ; extra == 'fignet'
Requires-Dist: webdataset >=0.2 ; extra == 'fignet'
Provides-Extra: launch
Requires-Dist: hydra-core >=1.2.0 ; extra == 'launch'
Requires-Dist: termcolor >=2.1.1 ; extra == 'launch'
Requires-Dist: wandb >=0.13.7 ; extra == 'launch'
Requires-Dist: mlflow >=2.1.1 ; extra == 'launch'
Requires-Dist: pydantic >=2.4.2 ; extra == 'launch'
Requires-Dist: imageio >=2.28.1 ; extra == 'launch'
Requires-Dist: moviepy >=1.0.3 ; extra == 'launch'
Provides-Extra: makani
Requires-Dist: torch-harmonics <0.7.1,>=0.6.5 ; extra == 'makani'
Requires-Dist: tensorly >=0.8.1 ; extra == 'makani'
Requires-Dist: tensorly-torch >=0.4.0 ; extra == 'makani'
